Azccriminal.py
azccriminal/azccriminal.py
azccriminal.egg-info/PKG-INFO
azccriminal.egg-info/SOURCES.txt
azccriminal.egg-info/dependency_links.txt
azccriminal.egg-info/top_level.txt