Metadata-Version: 2.1
Name: azccriminal
Version: 1.0.0
Summary: azccriminal web and database network traffic monitoring tool 
Author: Goychay_23
Author-email: goychay_23@gmail.com
